setup.py
kengine/__init__.py
kengine/handler.py
kengine/msg.py
kengine/user.py
kengine/ws.py
kengine.egg-info/PKG-INFO
kengine.egg-info/SOURCES.txt
kengine.egg-info/dependency_links.txt
kengine.egg-info/not-zip-safe
kengine.egg-info/requires.txt
kengine.egg-info/top_level.txt